symars/__init__.py
symars/dense.py
symars/meta.py
symars/scalar.py
symars/sparse.py
symars/dense_impl/__init__.py
symars/dense_impl/array.py
symars/dense_impl/faer.py
symars/dense_impl/nalgebra.py
symars/dense_impl/vecshape.py
symars-0.0.1.dist-info/LICENSE
symars-0.0.1.dist-info/METADATA
symars-0.0.1.dist-info/WHEEL
symars-0.0.1.dist-info/top_level.txt
symars-0.0.1.dist-info/RECORD
