Metadata-Version: 2.1
Name: symars
Version: 0.0.1
Summary: Generate Rust code with Sympy, for both scalars and matrices.
Author-email: Da1sypetals <da1sypetals.iota@gmail.com>
License: MIT
Project-URL: Homepage, https://github.com/Da1sypetals/Symars
License-File: LICENSE
Requires-Dist: sympy
Requires-Dist: sortedcontainers
